tests/test_web_leaf.py
webleaf/Leaf.py
webleaf/Web.py
webleaf/__init__.py
webleaf/model/TagModel.py
webleaf/model/TextModel.py
webleaf/model/WebGraphAutoEncoder.py
webleaf/model/__init__.py
webleaf/model/product_page_model_4_80.torch
webleaf/model/tag_embeddings.torch
webleaf-0.3.12.dist-info/LICENSE
webleaf-0.3.12.dist-info/METADATA
webleaf-0.3.12.dist-info/WHEEL
webleaf-0.3.12.dist-info/top_level.txt
webleaf-0.3.12.dist-info/RECORD
