Metadata-Version: 2.1
Name: webleaf
Version: 0.3.12
Summary: HTML DOM Tree Leaf Structure Identification Package
Author-email: Matthew Thomson <m7homson@gmail.com>
License: MIT License
Project-URL: homepage, https://thomsn.github.io/WebLeaf/webleaf.html
Project-URL: repository, https://github.com/thomsn/WebLeaf
Project-URL: documentation, https://thomsn.github.io/WebLeaf/webleaf.html
Keywords: dom,web,webscraping,leaf,beautifulsoup,html,tree,structure,embedding
License-File: LICENSE
Requires-Dist: lxml
Requires-Dist: cssselect
Requires-Dist: torch-geometric
Requires-Dist: torch==2.2.2
Requires-Dist: sentence-transformers
Requires-Dist: nltk
Requires-Dist: numpy
